{
  "clientes": [
    {
      "id": "8220",
      "dni": "13704203",
      "nombre": "Roberto",
      "apellido": "Benitez",
      "numero": "2236666677",
      "domicilio": "Libertad",
      "altura": "1033",
      "metodoPago": "Efectivo"
    },
    {
      "dni": "12560934",
      "nombre": "Norberto",
      "apellido": "Salomon",
      "numero": "2236778645",
      "domicilio": "Chubut",
      "altura": "1857",
      "metodoPago": "Tarjeta de Debito",
      "id": "47e7"
    },
    {
      "dni": "34786234",
      "nombre": "Rodrigo",
      "apellido": "Gimenez",
      "numero": "2239874510",
      "domicilio": "Colon",
      "altura": "1987",
      "metodoPago": "Tarjeta de Debito",
      "id": "2fa9"
    },
    {
      "id": "2a5e",
      "dni": "34125783",
      "nombre": "Facundo ",
      "apellido": "Rodriguez",
      "numero": "2237613498",
      "domicilio": "Ingenieros",
      "altura": "1243",
      "metodoPago": "Tarjeta de Credito"
    },
    {
      "id": "eea4",
      "dni": "22374981",
      "nombre": "Leonardo",
      "apellido": "Intrieri",
      "numero": "2237554912",
      "domicilio": "Estoril",
      "altura": "1009",
      "metodoPago": "Efectivo"
    },
    {
      "dni": "45820343",
      "nombre": "Santiago",
      "apellido": "Ude",
      "numero": "2236226805",
      "domicilio": "estoril ",
      "altura": "1045",
      "metodoPago": "Efectivo",
      "id": "64cc"
    },
    {
      "dni": "46874235",
      "nombre": "matias",
      "apellido": "antonelli",
      "numero": "2235982476",
      "domicilio": "Corderino",
      "altura": "1234",
      "metodoPago": "Efectivo",
      "id": "1de9"
    },
    {
      "dni": "44265003",
      "nombre": "Lautaro",
      "apellido": "Arias",
      "numero": "2236209845",
      "domicilio": "constitucion",
      "altura": "1654",
      "metodoPago": "Tarjeta de Credito",
      "id": "6ac8"
    },
    {
      "dni": "46874334",
      "nombre": "santiago",
      "apellido": "ayala",
      "numero": "2236227643",
      "domicilio": "estrada",
      "altura": "2004",
      "metodoPago": "Tarjeta de Credito",
      "id": "6a4d"
    },
    {
      "id": "b7ed",
      "dni": "13704567",
      "nombre": "Jose",
      "apellido": "Barrionuevo",
      "numero": "2236776545",
      "domicilio": "Dorrego",
      "altura": "1374",
      "metodoPago": "Tarjeta de Debito"
    }
  ],
  "presupuestos": [
    {
      "fecha": "2024-11-12",
      "descuento": 0,
      "items": [
        {
          "nombre": "Rectificacion de motor",
          "descripcion": "Desarmar, limpiar las piezas, realizar mantenimiento de rutina y volver a ensamblar.",
          "precioUnitario": 0,
          "precioManoObra": 350000,
          "precioFinal": 350000
        }
      ],
      "total": 350000,
      "id": "7.740476137146781"
    },
    {
      "fecha": "2024-11-12",
      "descuento": 10,
      "items": [
        {
          "nombre": "Rectificacion motor",
          "descripcion": "Desarmar el motor, limpiar las piezas, mantenimiento de rutina y volver a ensamblar",
          "precioUnitario": 0,
          "precioManoObra": 250000,
          "precioFinal": 250000
        },
        {
          "nombre": "Cambio de juntas",
          "descripcion": "Retirar y desechar las juntas viejas y colocarles las nuevas. RF56",
          "precioUnitario": 80000,
          "precioManoObra": 100000,
          "precioFinal": 180000
        }
      ],
      "total": 387000,
      "id": "4.194409230265461"
    },
    {
      "fecha": "2024-11-12",
      "descuento": 5,
      "items": [
        {
          "nombre": "Rectificacion motor",
          "descripcion": "Desarmar, limpiar las piezas, mantenimiento de rutina y ensamblar de nuevo.",
          "precioUnitario": 0,
          "precioManoObra": 100000,
          "precioFinal": 100000
        }
      ],
      "total": 95000,
      "id": "8.404510391197078"
    }
  ],
  "pedidos": [
    {
      "cliente": {
        "id": "6ac8",
        "dni": "45342134",
        "nombre": "Lautaro",
        "apellido": "Arias",
        "numero": "2236209845",
        "domicilio": "constitucion",
        "altura": "1654",
        "metodoPago": "Tarjeta de Credito"
      },
      "fechaEntrada": "2024-11-12T00:00:00.000Z",
      "fechaSalidaEstimada": "2024-11-16T00:00:00.000Z",
      "estado": "atrasado",
      "marcaAuto": "Ford",
      "modeloAuto": "F-150 R",
      "numeroSerie": "ABCDE12345",
      "descripcion": "Rectificacion de motor",
      "presupuesto": {
        "fecha": "2024-11-12",
        "descuento": 0,
        "items": [
          {
            "nombre": "Rectificacion de motor",
            "descripcion": "Desarmar, limpiar las piezas, realizar mantenimiento de rutina y volver a ensamblar.",
            "precioUnitario": 0,
            "precioManoObra": 350000,
            "precioFinal": 350000
          }
        ],
        "total": 350000,
        "id": "7.740476137146781"
      },
      "id": "c5f9"
    },
    {
      "cliente": {
        "id": "1de9",
        "dni": "46874235",
        "nombre": "matias",
        "apellido": "antonelli",
        "numero": "2235982476",
        "domicilio": "Corderino",
        "altura": "1234",
        "metodoPago": "Efectivo"
      },
      "fechaEntrada": "2024-11-10T00:00:00.000Z",
      "fechaSalidaEstimada": "2024-11-15T00:00:00.000Z",
      "estado": "atrasado",
      "marcaAuto": "chevrolet",
      "modeloAuto": "corsa 2011",
      "numeroSerie": "JHGER47613",
      "descripcion": "Rectificación de motor y cambio de juntas.",
      "presupuesto": {
        "fecha": "2024-11-12",
        "descuento": 10,
        "items": [
          {
            "nombre": "Rectificacion motor",
            "descripcion": "Desarmar el motor, limpiar las piezas, mantenimiento de rutina y volver a ensamblar",
            "precioUnitario": 0,
            "precioManoObra": 250000,
            "precioFinal": 250000
          },
          {
            "nombre": "Cambio de juntas",
            "descripcion": "Retirar y desechar las juntas viejas y colocarles las nuevas. RF56",
            "precioUnitario": 80000,
            "precioManoObra": 100000,
            "precioFinal": 180000
          }
        ],
        "total": 387000,
        "id": "4.194409230265461"
      },
      "id": "9cc7"
    },
    {
      "cliente": {
        "dni": "34786234",
        "nombre": "Rodrigo",
        "apellido": "Gimenez",
        "numero": "2239874510",
        "domicilio": "Colon",
        "altura": "1987",
        "metodoPago": "Tarjeta de Debito",
        "id": "2fa9"
      },
      "fechaEntrada": "2024-11-05T00:00:00.000Z",
      "fechaSalidaEstimada": "2024-11-12T00:00:00.000Z",
      "estado": "atrasado",
      "marcaAuto": "Fiat",
      "modeloAuto": "500",
      "numeroSerie": "HDFNE45812",
      "descripcion": "Rectificacion motor.",
      "presupuesto": {
        "fecha": "2024-11-12",
        "descuento": 5,
        "items": [
          {
            "nombre": "Rectificacion motor",
            "descripcion": "Desarmar, limpiar las piezas, mantenimiento de rutina y ensamblar de nuevo.",
            "precioUnitario": 0,
            "precioManoObra": 100000,
            "precioFinal": 100000
          }
        ],
        "total": 95000,
        "id": "8.404510391197078"
      },
      "id": "be0d"
    }
  ]
}