{
  "clientes": [
    {
      "dni": "44265003",
      "nombre": "Ernesto",
      "apellido": "Arias",
      "numero": "2236697212",
      "domicilio": "Padre Dutto",
      "altura": "321",
      "metodoPago": "Efectivo",
      "id": "a5b7"
    },
    {
      "id": "0694",
      "dni": "44578006",
      "nombre": "Matias",
      "apellido": "Bellonio",
      "numero": "2236687894",
      "domicilio": "Perez Bulnes",
      "altura": "123",
      "metodoPago": "Tarjeta de Credito"
    },
    {
      "dni": "44135008",
      "nombre": "Leonardo",
      "apellido": "Indrieri",
      "numero": "2239987515",
      "domicilio": "Perez Bulnes",
      "altura": "111",
      "metodoPago": "Tarjeta de Credito"
    }
  ],
  "presupuestos": [
    {
      "id": "6.686939354929049",
      "fecha": "2024-11-08",
      "descuento": 11,
      "items": [
        {
          "nombre": "12345",
          "descripcion": "123456",
          "precioUnitario": 12,
          "precioManoObra": 12,
          "precioFinal": 24
        },
        {
          "nombre": "123123",
          "descripcion": "123123",
          "precioUnitario": 123123,
          "precioManoObra": 231231,
          "precioFinal": 123123123123
        }
      ]
    },
    {
      "id": "6.686939354921055",
      "fecha": "2024-12-08",
      "descuento": 5,
      "items": [
        {
          "nombre": "pruebita1",
          "descripcion": "sdafasdfasdfadsf",
          "precioUnitario": 33,
          "precioManoObra": 33,
          "precioFinal": 33
        }
      ]
    },
    {
      "id": "6.686939405521055",
      "fecha": "2024-10-10",
      "descuento": 90,
      "items": [
        {
          "nombre": "pruebita55",
          "descripcion": "dsdsfg",
          "precioUnitario": 55,
          "precioManoObra": 55,
          "precioFinal": 55
        }
      ]
    },
    {
      "id": "6.798839405521055",
      "fecha": "2024-11-10",
      "descuento": 40,
      "items": [
        {
          "nombre": "asdfasdfasdf",
          "descripcion": "dsasdfasdfasdfasdfasdfasdfasdfasdfasfasfasdfasdfddsfg",
          "precioUnitario": 44,
          "precioManoObra": 545,
          "precioFinal": 5544
        }
      ]
    },
    {
      "id": "0.899102478027638",
      "fecha": "2024-11-06",
      "descuento": 12,
      "items": [
        {
          "nombre": "asdfsadf",
          "descripcion": "asdfsadf",
          "precioUnitario": 43,
          "precioManoObra": 455,
          "precioFinal": 34
        }
      ]
    },
    {
      "id": "8.541733259893157",
      "fecha": "2024-11-15",
      "descuento": 2,
      "items": [
        {
          "nombre": "sadfasd",
          "descripcion": "asdfasdf",
          "precioUnitario": 23,
          "precioManoObra": 123,
          "precioFinal": 232
        }
      ]
    },
    {
      "id": "8.844854462548021",
      "fecha": "2024-11-22",
      "descuento": 1212,
      "items": [
        {
          "nombre": "asdfasdf",
          "descripcion": "sadfsadf",
          "precioUnitario": 12,
          "precioManoObra": 12,
          "precioFinal": 12
        },
        {
          "nombre": "dsfasdf",
          "descripcion": "asdfadsf",
          "precioUnitario": 12,
          "precioManoObra": 1212,
          "precioFinal": 1212
        }
      ]
    },
    {
      "id": "3.6822684868130695",
      "fecha": "2024-11-09",
      "descuento": 12,
      "items": [
        {
          "nombre": "Mantenimiento Valvula",
          "descripcion": "KFJASDFKJ",
          "precioUnitario": 250,
          "precioManoObra": 300,
          "precioFinal": 2000
        }
      ]
    },
    {
      "id": "5.478542631851246",
      "fecha": "2024-11-09",
      "descuento": 23,
      "items": [
        {
          "nombre": "asdf",
          "descripcion": "fdasf",
          "precioUnitario": 34,
          "precioManoObra": 4,
          "precioFinal": 34
        }
      ]
    }
  ],
  "pedidos": [
    {
      "cliente": {
        "id": "0694",
        "dni": "44578006",
        "nombre": "Matias",
        "apellido": "Bellonio",
        "numero": "2236687894",
        "domicilio": "Perez Bulnes",
        "altura": "123",
        "metodoPago": "Tarjeta de Credito"
      },
      "fechaEntrada": "2024-11-05T00:00:00.000Z",
      "fechaSalidaEstimada": "2024-11-13T00:00:00.000Z",
      "estado": "activo",
      "marcaAuto": "Ford",
      "modeloAuto": "Falcon",
      "numeroSerie": "efh23t423423",
      "descripcion": "Rectificar Cigueñal",
      "presupuesto": {
        "id": "6.798839405521055",
        "fecha": "2024-11-10",
        "descuento": 40,
        "items": [
          {
            "nombre": "asdfasdfasdf",
            "descripcion": "dsasdfasdfasdfasdfasdfasdfasdfasdfasfasfasdfasdfddsfg",
            "precioUnitario": 44,
            "precioManoObra": 545,
            "precioFinal": 5544
          }
        ]
      },
      "id": "84ed"
    },
    {
      "cliente": {
        "id": "a5b7",
        "dni": "44265003",
        "nombre": "Lautaro",
        "apellido": "Arias",
        "numero": "2236697212",
        "domicilio": "Padre Dutto",
        "altura": "321",
        "metodoPago": "Efectivo"
      },
      "fechaEntrada": "2024-10-06T00:00:00.000Z",
      "fechaSalidaEstimada": "2024-11-08T00:00:00.000Z",
      "estado": "atrasado",
      "marcaAuto": "asdf",
      "modeloAuto": "asdf",
      "numeroSerie": "asdf",
      "descripcion": "sadfsadfasdfsadfdsafdsfsadf",
      "presupuesto": {
        "fecha": "2024-11-22",
        "descuento": 1212,
        "items": [
          {
            "nombre": "asdfasdf",
            "descripcion": "sadfsadf",
            "precioUnitario": 12,
            "precioManoObra": 12,
            "precioFinal": 12
          },
          {
            "nombre": "dsfasdf",
            "descripcion": "asdfadsf",
            "precioUnitario": 12,
            "precioManoObra": 1212,
            "precioFinal": 1212
          }
        ],
        "id": "8.844854462548021"
      },
      "id": "2901"
    },
    {
      "id": "d5e3",
      "cliente": {
        "id": "a5b7",
        "dni": "44265003",
        "nombre": "Lautaro",
        "apellido": "Arias",
        "numero": "2236697212",
        "domicilio": "Padre Dutto",
        "altura": "321",
        "metodoPago": "Efectivo"
      },
      "fechaEntrada": "2024-11-30T00:00:00.000Z",
      "fechaSalidaEstimada": "2024-12-08T00:00:00.000Z",
      "estado": "activo",
      "marcaAuto": "Ford",
      "modeloAuto": "F-150 R",
      "numeroSerie": "123456789",
      "descripcion": "Mantenimiento de ruedas, suspension y aceite.",
      "presupuesto": {
        "fecha": "2024-11-09",
        "descuento": 12,
        "items": [
          {
            "nombre": "Mantenimiento Valvula",
            "descripcion": "KFJASDFKJ",
            "precioUnitario": 250,
            "precioManoObra": 300,
            "precioFinal": 2000
          }
        ],
        "id": "3.6822684868130695"
      }
    },
    {
      "id": "40f5",
      "cliente": {
        "id": "a5b7",
        "dni": "44265003",
        "nombre": "Lautaro",
        "apellido": "Arias",
        "numero": "2236697212",
        "domicilio": "Padre Dutto",
        "altura": "321",
        "metodoPago": "Efectivo"
      },
      "fechaEntrada": "2024-11-06T00:00:00.000Z",
      "fechaSalidaEstimada": "2024-11-24T00:00:00.000Z",
      "estado": "activo",
      "marcaAuto": "ASD",
      "modeloAuto": "asdfasdf",
      "numeroSerie": "342234",
      "descripcion": "dsafsadfasf",
      "presupuesto": {
        "fecha": "2024-11-09",
        "descuento": 23,
        "items": [
          {
            "nombre": "asdf",
            "descripcion": "fdasf",
            "precioUnitario": 34,
            "precioManoObra": 4,
            "precioFinal": 34
          }
        ],
        "id": "5.478542631851246"
      }
    }
  ]
}